jbisect/__init__.py
jbisect/numpy.py
jbisect/py.typed
jbisect-0.4.0.dist-info/LICENSE
jbisect-0.4.0.dist-info/METADATA
jbisect-0.4.0.dist-info/WHEEL
jbisect-0.4.0.dist-info/RECORD
